resbaz/__init__.py
resbaz/certificate.py
resbaz-0.0.6.dist-info/METADATA
resbaz-0.0.6.dist-info/WHEEL
resbaz-0.0.6.dist-info/licenses/LICENSE
resbaz-0.0.6.dist-info/RECORD
